MANIFEST.in
README.md
meta.json
setup.py
en_nligraphspacy/__init__.py
en_nligraphspacy/meta.json
en_nligraphspacy.egg-info/PKG-INFO
en_nligraphspacy.egg-info/SOURCES.txt
en_nligraphspacy.egg-info/dependency_links.txt
en_nligraphspacy.egg-info/entry_points.txt
en_nligraphspacy.egg-info/not-zip-safe
en_nligraphspacy.egg-info/requires.txt
en_nligraphspacy.egg-info/top_level.txt
en_nligraphspacy/en_nligraphspacy-0.0.1/README.md
en_nligraphspacy/en_nligraphspacy-0.0.1/config.cfg
en_nligraphspacy/en_nligraphspacy-0.0.1/meta.json
en_nligraphspacy/en_nligraphspacy-0.0.1/tokenizer
en_nligraphspacy/en_nligraphspacy-0.0.1/ner/cfg
en_nligraphspacy/en_nligraphspacy-0.0.1/ner/model
en_nligraphspacy/en_nligraphspacy-0.0.1/ner/moves
en_nligraphspacy/en_nligraphspacy-0.0.1/tok2vec/cfg
en_nligraphspacy/en_nligraphspacy-0.0.1/tok2vec/model
en_nligraphspacy/en_nligraphspacy-0.0.1/vocab/key2row
en_nligraphspacy/en_nligraphspacy-0.0.1/vocab/lookups.bin
en_nligraphspacy/en_nligraphspacy-0.0.1/vocab/strings.json
en_nligraphspacy/en_nligraphspacy-0.0.1/vocab/vectors
en_nligraphspacy/en_nligraphspacy-0.0.1/vocab/vectors.cfg