Metadata-Version: 2.1
Name: en-nligraphspacy
Version: 0.0.1
Summary: Knowledge graph in Spacy
Home-page: https://github.com/Vishnunkumar/nligraphspacy
Author: Vishnu
Author-email: vishnunkumar25@gmail.com
